rill/__init__.py
rill/py.typed
rill/rill.py
rill/tests.py
rill-0.1.2.dist-info/LICENSE
rill-0.1.2.dist-info/METADATA
rill-0.1.2.dist-info/WHEEL
rill-0.1.2.dist-info/top_level.txt
rill-0.1.2.dist-info/RECORD
