Metadata-Version: 2.1
Name: rill
Version: 0.1.2
Summary: Simple text-stream processing functionality
Home-page: http://github.com/Dobiasd/rill
Author: Tobias Hermann
Author-email: editgym@gmail.com
License: UNKNOWN
Platform: UNKNOWN
Classifier: Programming Language :: Python :: 3
Classifier: License :: OSI Approved :: MIT License
Classifier: Operating System :: OS Independent
Requires-Python: >=3
